README.md
setup.py
BOHB_HPO.egg-info/PKG-INFO
BOHB_HPO.egg-info/SOURCES.txt
BOHB_HPO.egg-info/dependency_links.txt
BOHB_HPO.egg-info/requires.txt
BOHB_HPO.egg-info/top_level.txt
bohb/__init__.py
bohb/bohb.py
bohb/configspace.py